modules/__init__.py
modules/comment_find.py
modules/headers_view.py
modules/img_source_find.py
modules/script_source_find.py
webctf-0.0.0.dist-info/LICENSE
webctf-0.0.0.dist-info/METADATA
webctf-0.0.0.dist-info/WHEEL
webctf-0.0.0.dist-info/entry_points.txt
webctf-0.0.0.dist-info/top_level.txt
webctf-0.0.0.dist-info/RECORD
