Metadata-Version: 2.1
Name: webctf
Version: 0.0.0
Summary: HTML source scraper
Home-page: https://github.com/xnomas/web-ctf-help
Author: Jakub Osmani
License: GPL-3.0 License
Keywords: ctf,html,scraper
Platform: UNKNOWN
Classifier: Operating System :: OS Independent
Classifier: Programming Language :: Python
Classifier: Programming Language :: Python :: 3
Classifier: Programming Language :: Python :: 3.6
Classifier: Programming Language :: Python :: 3.7
Classifier: Programming Language :: Python :: 3.8
Classifier: Programming Language :: Python :: 3.9
Requires-Python: >=3.6.1
